meshtastic/.gitignore
meshtastic/__init__.py
meshtastic/__main__.py
meshtastic/analysis/__init__.py
meshtastic/analysis/__main__.py
meshtastic/ble_interface.py
meshtastic/mesh_interface.py
meshtastic/mt_config.py
meshtastic/node.py
meshtastic/powermon/__init__.py
meshtastic/powermon/power_supply.py
meshtastic/powermon/ppk2.py
meshtastic/powermon/riden.py
meshtastic/powermon/sim.py
meshtastic/powermon/stress.py
meshtastic/protobuf/__init__.py
meshtastic/protobuf/admin_pb2.py
meshtastic/protobuf/admin_pb2.pyi
meshtastic/protobuf/apponly_pb2.py
meshtastic/protobuf/apponly_pb2.pyi
meshtastic/protobuf/atak_pb2.py
meshtastic/protobuf/atak_pb2.pyi
meshtastic/protobuf/cannedmessages_pb2.py
meshtastic/protobuf/cannedmessages_pb2.pyi
meshtastic/protobuf/channel_pb2.py
meshtastic/protobuf/channel_pb2.pyi
meshtastic/protobuf/clientonly_pb2.py
meshtastic/protobuf/clientonly_pb2.pyi
meshtastic/protobuf/config_pb2.py
meshtastic/protobuf/config_pb2.pyi
meshtastic/protobuf/connection_status_pb2.py
meshtastic/protobuf/connection_status_pb2.pyi
meshtastic/protobuf/device_ui_pb2.py
meshtastic/protobuf/device_ui_pb2.pyi
meshtastic/protobuf/deviceonly_pb2.py
meshtastic/protobuf/deviceonly_pb2.pyi
meshtastic/protobuf/interdevice_pb2.py
meshtastic/protobuf/interdevice_pb2.pyi
meshtastic/protobuf/localonly_pb2.py
meshtastic/protobuf/localonly_pb2.pyi
meshtastic/protobuf/mesh_pb2.py
meshtastic/protobuf/mesh_pb2.pyi
meshtastic/protobuf/module_config_pb2.py
meshtastic/protobuf/module_config_pb2.pyi
meshtastic/protobuf/mqtt_pb2.py
meshtastic/protobuf/mqtt_pb2.pyi
meshtastic/protobuf/nanopb_pb2.py
meshtastic/protobuf/nanopb_pb2.pyi
meshtastic/protobuf/paxcount_pb2.py
meshtastic/protobuf/paxcount_pb2.pyi
meshtastic/protobuf/portnums_pb2.py
meshtastic/protobuf/portnums_pb2.pyi
meshtastic/protobuf/powermon_pb2.py
meshtastic/protobuf/powermon_pb2.pyi
meshtastic/protobuf/remote_hardware_pb2.py
meshtastic/protobuf/remote_hardware_pb2.pyi
meshtastic/protobuf/rtttl_pb2.py
meshtastic-2.7.6.dist-info/METADATA
meshtastic-2.7.6.dist-info/WHEEL
meshtastic-2.7.6.dist-info/entry_points.txt
meshtastic-2.7.6.dist-info/licenses/LICENSE.md
meshtastic-2.7.6.dist-info/RECORD
