Metadata-Version: 2.4
Name: meshtastic
Version: 2.7.6
Summary: Python API & client shell for talking to Meshtastic devices
License: GPL-3.0-only
License-File: LICENSE.md
Author: Meshtastic Developers
Author-email: contact@meshtastic.org
Requires-Python: >=3.9,<3.15
Classifier: License :: OSI Approved :: GNU General Public License v3 (GPLv3)
Classifier: Programming Language :: Python :: 3
Classifier: Programming Language :: Python :: 3.9
Classifier: Programming Language :: Python :: 3.10
Classifier: Programming Language :: Python :: 3.11
Classifier: Programming Language :: Python :: 3.12
Classifier: Programming Language :: Python :: 3.13
Classifier: Programming Language :: Python :: 3.14
Provides-Extra: analysis
Provides-Extra: cli
Provides-Extra: tunnel
Requires-Dist: argcomplete (>=3.5.2,<4.0.0) ; extra == "cli"
Requires-Dist: bleak (>=0.22.3)
Requires-Dist: dash (>=2.17.1,<3.0.0) ; extra == "analysis"
Requires-Dist: dash-bootstrap-components (>=1.6.0,<2.0.0) ; extra == "analysis"
Requires-Dist: dotmap (>=1.3.30,<2.0.0) ; extra == "cli"
Requires-Dist: packaging (>=24.0,<25.0)
Requires-Dist: pandas (>=2.2.2,<3.0.0) ; extra == "analysis"
Requires-Dist: pandas-stubs (>=2.2.2.240603,<3.0.0.0) ; extra == "analysis"
Requires-Dist: print-color (>=0.4.6,<0.5.0) ; extra == "cli"
Requires-Dist: protobuf (>=4.21.12)
Requires-Dist: pypubsub (>=4.0.3,<5.0.0)
Requires-Dist: pyqrcode (>=1.2.1,<2.0.0) ; extra == "cli"
Requires-Dist: pyserial (>=3.5,<4.0)
Requires-Dist: pytap2 (>=2.3.0,<3.0.0) ; extra == "tunnel"
Requires-Dist: pyyaml (>=6.0.1,<7.0.0)
Requires-Dist: requests (>=2.31.0,<3.0.0)
Requires-Dist: tabulate (>=0.9.0,<0.10.0)
Requires-Dist: wcwidth (>=0.2.13,<0.3.0) ; extra == "cli"
